yams/__init__.py
yams/_exceptions.py
yams/buildobjs.py
yams/constraints.py
yams/diff.py
yams/interfaces.py
yams/py.typed
yams/reader.py
yams/schema.py
yams/schema2dot.py
yams/schema_exporters.py
yams/serialize.py
yams/tools.py
yams/types.py
yams/xy.py
yams-2.0.1.data/scripts/yams-check
yams-2.0.1.data/scripts/yams-view
yams-2.0.1.dist-info/licenses/COPYING
yams-2.0.1.dist-info/licenses/COPYING.LESSER
yams-2.0.1.dist-info/METADATA
yams-2.0.1.dist-info/WHEEL
yams-2.0.1.dist-info/top_level.txt
yams-2.0.1.dist-info/RECORD
