Metadata-Version: 2.4
Name: yams
Version: 2.0.1
Summary: entity / relation schema
Home-page: https://forge.extranet.logilab.fr/open-source/yams
Author: Logilab
Author-email: devel@logilab.fr
License: LGPL
Classifier: Programming Language :: Python
Classifier: Programming Language :: Python :: 3
Classifier: Programming Language :: Python :: 3 :: Only
Requires-Python: >=3.9.2
License-File: COPYING
License-File: COPYING.LESSER
Requires-Dist: setuptools
Requires-Dist: logilab-common<3.0.0,>=2.1.0
Requires-Dist: typing-extensions<5.0.0,>=4.14.0
Requires-Dist: python-dateutil>=2.9.0
Requires-Dist: importlib_metadata; python_version < "3.10"
Dynamic: author
Dynamic: author-email
Dynamic: classifier
Dynamic: description
Dynamic: home-page
Dynamic: license
Dynamic: license-file
Dynamic: requires-dist
Dynamic: requires-python
Dynamic: summary
